nvidia_tao_client-6.25.11.dist-info/licenses/LICENSE
tao_cli/__init__.py
tao_cli/common.py
tao_cli/enum_constants.py
tao_cli/tao.py
tao_cli/cli_actions/__init__.py
tao_cli/cli_actions/actions.py
tao_cli/cli_actions/network_click_wrapper.py
tao_sdk/__init__.py
tao_sdk/client.py
tao_sdk/exceptions.py
tao_sdk/schemas.py
nvidia_tao_client-6.25.11.dist-info/METADATA
nvidia_tao_client-6.25.11.dist-info/WHEEL
nvidia_tao_client-6.25.11.dist-info/entry_points.txt
nvidia_tao_client-6.25.11.dist-info/top_level.txt
nvidia_tao_client-6.25.11.dist-info/RECORD
