Metadata-Version: 2.4
Name: nvidia-tao-client
Version: 6.25.11
Summary: NVIDIA's package for using TAO-REST-API via TAO-Client.
Author: Varun Praveen
Author-email: vpraveen@nvidia.com
License:                                                          NVIDIA AI PRODUCT AGREEMENT
Keywords: nvidia,tao,api
Classifier: Intended Audience :: Developers
Classifier: Topic :: Software Development :: Libraries
Classifier: Topic :: Software Development :: Libraries :: Python Modules
Classifier: Environment :: Console
Classifier: Operating System :: POSIX :: Linux
Classifier: License :: Other/Proprietary License
Classifier: Programming Language :: Python :: 3
Classifier: Topic :: Scientific/Engineering :: Artificial Intelligence
License-File: LICENSE
Requires-Dist: click>=8.1.8
Requires-Dist: configparser>=7.1.0
Requires-Dist: requests>=2.32.3
Requires-Dist: nvidia-tao-core==6.25.11
Dynamic: author
Dynamic: author-email
Dynamic: classifier
Dynamic: keywords
Dynamic: license-file
